jsonreg/__init__.py
jsonreg/__main__.py
jsonreg-0.1.5.dist-info/LICENSE
jsonreg-0.1.5.dist-info/METADATA
jsonreg-0.1.5.dist-info/WHEEL
jsonreg-0.1.5.dist-info/top_level.txt
jsonreg-0.1.5.dist-info/RECORD
