Metadata-Version: 2.1
Name: jsonreg
Version: 0.1.5
Summary: Quickly create json keys to store data
Home-page: https://github.com/awesomelewis2007/jsonreg/
Author: Lewis Evans
License: GNU
Platform: UNKNOWN
License-File: LICENSE
